poetry_test_project_2/__init__.py
poetry_test_project_2/main.py
poetry_test_project_2/random_module.py
poetry_test_project_2-0.1.1.dist-info/METADATA
poetry_test_project_2-0.1.1.dist-info/WHEEL
poetry_test_project_2-0.1.1.dist-info/RECORD
