Metadata-Version: 2.1
Name: poetry-test-project-2
Version: 0.1.1
Summary: Just a dummy project to test packaging. This package will be removed.
Author: Joost Berkhout
Author-email: joost.berkhout@vu.nl
Requires-Python: >=3.10,<4.0
Classifier: Programming Language :: Python :: 3
Classifier: Programming Language :: Python :: 3.10
Classifier: Programming Language :: Python :: 3.11
Classifier: Programming Language :: Python :: 3.12
Requires-Dist: ipython (>=8.21.0,<9.0.0)
Requires-Dist: pre-commit (>=3.6.1,<4.0.0)
Requires-Dist: pytest (>=8.0.0,<9.0.0)
